mesh_kit/__init__.py
mesh_kit/cmd/__init__.py
mesh_kit/cmd/__main__.py
mesh_kit/cmd/registration/__init__.py
mesh_kit/cmd/registration/__main__.py
mesh_kit/cmd/registration/densify.py
mesh_kit/common/cli.py
mesh_kit/examples/__init__.py
mesh_kit/examples/sculptor/.gitignore
mesh_kit/examples/sculptor/Makefile
mesh_kit/examples/sculptor/README.md
mesh_kit/examples/sculptor/__init__.py
mesh_kit/examples/sculptor/cmd/CT_to_mesh.py
mesh_kit/examples/sculptor/cmd/align.py
mesh_kit/examples/sculptor/cmd/densify.py
mesh_kit/examples/sculptor/cmd/template/face.py
mesh_kit/examples/sculptor/cmd/template/skull.py
mesh_kit/examples/sculptor/scripts/manual.sh
mesh_kit/transform/__init__.py
mesh_kit/transform/similarity.py
mesh_kit-0.0.1.dist-info/METADATA
mesh_kit-0.0.1.dist-info/WHEEL
mesh_kit-0.0.1.dist-info/entry_points.txt
mesh_kit-0.0.1.dist-info/RECORD
