Metadata-Version: 2.1
Name: mesh-kit
Version: 0.0.1
Summary: 
Author: liblaf
Author-email: i@liblaf.me
Requires-Python: >=3.10,<3.13
Classifier: Programming Language :: Python :: 3
Classifier: Programming Language :: Python :: 3.10
Classifier: Programming Language :: Python :: 3.11
Requires-Dist: matplotlib (>=3.8.0,<4.0.0)
Requires-Dist: numpy (>=1.26.1,<2.0.0)
Requires-Dist: opencv-python (>=4.8.1.78,<5.0.0.0)
Requires-Dist: pynrrd (>=1.0.0,<2.0.0)
Requires-Dist: pyvista[all] (>=0.42.3,<0.43.0)
Requires-Dist: trimesh[all] (>=4.0.1,<5.0.0)
Requires-Dist: typer (>=0.9.0,<0.10.0)
